mcmtest/__init__.py
mcmtest/lib/__init__.py
mcmtest/lib/condor.py
mcmtest/lib/helpers.py
mcmtest/lib/logging.py
mcmtest/loganalyzer/__init__.py
mcmtest/loganalyzer/loganalyzer.py
mcmtest/submitter/__init__.py
mcmtest/submitter/submitter.py
mcmtest-0.0.3.data/scripts/mcmanalyze
mcmtest-0.0.3.data/scripts/mcmlog
mcmtest-0.0.3.data/scripts/mcmsubmit
mcmtest-0.0.3.dist-info/LICENSE
mcmtest-0.0.3.dist-info/METADATA
mcmtest-0.0.3.dist-info/WHEEL
mcmtest-0.0.3.dist-info/top_level.txt
mcmtest-0.0.3.dist-info/RECORD
