Metadata-Version: 2.1
Name: mcmtest
Version: 0.0.3
Summary: Package for local McM test submissions using HTCondor.
Home-page: UNKNOWN
Author: Alp Akpinar
Author-email: aakpinar@bu.edu
License: UNKNOWN
Platform: UNKNOWN
Requires-Dist: htcondor
Requires-Dist: tabulate
Requires-Dist: numpy
